xltpl/__init__.py
xltpl/base.py
xltpl/basex.py
xltpl/cellcontext.py
xltpl/celltag.py
xltpl/cli.py
xltpl/config.py
xltpl/filters.py
xltpl/image.py
xltpl/jinja.py
xltpl/merger.py
xltpl/mergerx.py
xltpl/misc.py
xltpl/nodemap.py
xltpl/patchx.py
xltpl/richtexthandler.py
xltpl/sheetresource.py
xltpl/utils.py
xltpl/writer.py
xltpl/writermixin.py
xltpl/writerx.py
xltpl/xlext.py
xltpl/xlnode.py
xltpl/ynext.py
mog_xltpl-1.0.0.dist-info/METADATA
mog_xltpl-1.0.0.dist-info/WHEEL
mog_xltpl-1.0.0.dist-info/entry_points.txt
mog_xltpl-1.0.0.dist-info/licenses/LICENSE
mog_xltpl-1.0.0.dist-info/RECORD
