Metadata-Version: 2.4
Name: mog-xltpl
Version: 1.0.0
Summary: A Windows-only xltpl fork that preserves VBA, images, and complex Excel formatting using COM
Project-URL: Homepage, https://github.com/mogwai-dev/mog-xltpl
Project-URL: Repository, https://github.com/mogwai-dev/mog-xltpl
Project-URL: Original, https://github.com/zhangyu836/xltpl
Project-URL: Issues, https://github.com/mogwai-dev/mog-xltpl/issues
Project-URL: Documentation, https://github.com/mogwai-dev/mog-xltpl#readme
Author: mogwai
License: MIT License
License-File: LICENSE
Keywords: COM,Excel,VBA,Windows,formatting,jinja2,openpyxl,preserve,spreadsheet,template,workbook,xls,xlsx
Classifier: Development Status :: 5 - Production/Stable
Classifier: Intended Audience :: Developers
Classifier: License :: OSI Approved :: MIT License
Classifier: Operating System :: Microsoft :: Windows
Classifier: Programming Language :: Python :: 3
Classifier: Programming Language :: Python :: 3.8
Classifier: Programming Language :: Python :: 3.9
Classifier: Programming Language :: Python :: 3.10
Classifier: Programming Language :: Python :: 3.11
Classifier: Programming Language :: Python :: 3.12
Classifier: Programming Language :: Python :: 3.13
Classifier: Topic :: Office/Business
Classifier: Topic :: Software Development :: Libraries :: Python Modules
Classifier: Topic :: Text Processing :: Markup
Requires-Python: >=3.8
Requires-Dist: jinja2
Requires-Dist: openpyxl>=3.1.0
Requires-Dist: pillow>=9.0.0
Requires-Dist: pywin32>=311
Requires-Dist: pyyaml>=6.0.3
Requires-Dist: six
Requires-Dist: tomli
Requires-Dist: xlrd>=1.2.0
Requires-Dist: xlwt>=1.3.0
Provides-Extra: test
Requires-Dist: pytest>=7; extra == 'test'
